Metadata-Version: 2.1
Name: forbiddenfluent
Version: 0.1.1
Summary: Adds iteration methods like zip, filter, apply to built-in Python collections in a fluent programming style.
Home-page: https://github.com/nickdelgrosso/forbiddenfluent
Author: Nicholas A. Del Grosso
Author-email: delgrosso.nick@gmail.com
License: GNU General Public License, Version 3
Platform: UNKNOWN
Classifier: Programming Language :: Python :: 3
Requires-Python: >=3.6
